sanic_mako.py
Sanic_Mako-0.7.0.dist-info/LICENSE
Sanic_Mako-0.7.0.dist-info/METADATA
Sanic_Mako-0.7.0.dist-info/WHEEL
Sanic_Mako-0.7.0.dist-info/top_level.txt
Sanic_Mako-0.7.0.dist-info/RECORD
